{
  "name": "castle-falkenstein",
  "version": "0.4.0",
  "title": "Castle Falkenstein",
  "description": "FoundryVTT system for Castle Falkenstein.",
  "minimumCoreVersion": "9",
  "compatibleCoreVersion": "9",
  "authors": [ "admiralnlson" ],
  "esmodules": [
    "src/lib/socketlib/socketlib.js",
    "src/castle-falkenstein.mjs"
  ],
  "styles": ["src/css/castle-falkenstein.css"],
  "packs": [
    {
      "label": "Abilities - Corebook",
      "path": "build/packs/abilities-corebook.db",
      "name": "abilities-corebook",
      "type": "Item"
    },
    {
      "label": "Lorebook: Manuscriptum Mentallis",
      "path": "build/packs/spells-1.db",
      "name": "spells-1",
      "type": "Item"
    },
    {
      "label": "Lorebook: Ritual Writing of Psychic Binding",
      "path": "build/packs/spells-2.db",
      "name": "spells-2",
      "type": "Item"
    },
    {
      "label": "Lorebook: Agrivicca Rexus' Realm of Illusion",
      "path": "build/packs/spells-3.db",
      "name": "spells-3",
      "type": "Item"
    },
    {
      "label": "Lorebook: Megron's Realm of Dreaming",
      "path": "build/packs/spells-4.db",
      "name": "spells-4",
      "type": "Item"
    },
    {
      "label": "Lorebook: Realm of The Unknown Mind",
      "path": "build/packs/spells-5.db",
      "name": "spells-5",
      "type": "Item"
    },
    {
      "label": "Lorebook: Libram of Mystic Transformation",
      "path": "build/packs/spells-6.db",
      "name": "spells-6",
      "type": "Item"
    },
    {
      "label": "Lorebook: The Manuscriptum Universal Alchemic",
      "path": "build/packs/spells-7.db",
      "name": "spells-7",
      "type": "Item"
    },
    {
      "label": "Lorebook: Osman's Tome of Physical Movement",
      "path": "build/packs/spells-8.db",
      "name": "spells-8",
      "type": "Item"
    },
    {
      "label": "Lorebook: Libram of Temporal Control",
      "path": "build/packs/spells-9.db",
      "name": "spells-9",
      "type": "Item"
    },
    {
      "label": "Lorebook: Libram of Summonation",
      "path": "build/packs/spells-10.db",
      "name": "spells-10",
      "type": "Item"
    },
    {
      "label": "Lorebook: LeRoeun's Scrolls of Dimensional Movement",
      "path": "build/packs/spells-11.db",
      "name": "spells-11",
      "type": "Item"
    },
    {
      "label": "Lorebook: Dark Libram of Necromancy",
      "path": "build/packs/spells-12.db",
      "name": "spells-12",
      "type": "Item"
    },
    {
      "label": "Lorebook: Manuscript of Paranormal Divination",
      "path": "build/packs/spells-13.db",
      "name": "spells-13",
      "type": "Item"
    },
    {
      "label": "Lorebook: Manuscript of Elemental Shaping",
      "path": "build/packs/spells-14.db",
      "name": "spells-14",
      "type": "Item"
    },
    {
      "label": "Lorebook: Burton's On the Raised Forces of Nature",
      "path": "build/packs/spells-15.db",
      "name": "spells-15",
      "type": "Item"
    }
  ],
  "languages": [
    {
      "lang": "en",
      "name": "English",
      "path": "lang/en.json"
    },
    {
      "lang": "fr",
      "name": "French",
      "path": "lang/fr.json"
    }
  ],
  "dependencies": [ 
    {
      "name": "monarch",
      "type": "module",
      "manifest": "https://github.com/zeel01/monarch/releases/latest/download/module.json"
    },
    {
      "name": "lib-wrapper",
      "type": "module",
      "manifest": "https://github.com/ruipin/fvtt-lib-wrapper/releases/latest/download/module.json"
    }
  ],
  "socket": true,
  "manifest": "https://github.com/admiralnlson/castle-falkenstein-fvtt/releases/latest/download/system.json",
  "url": "https://github.com/admiralnlson/castle-falkenstein-fvtt",
  "download": "https://github.com/admiralnlson/castle-falkenstein-fvtt/releases/latest/download/castle-falkenstein.zip",
  "license": "https://github.com/admiralnlson/castle-falkenstein-fvtt/blob/master/LICENSE",
  "readme": "https://github.com/admiralnlson/castle-falkenstein-fvtt/blob/master/README.md",
  "bugs": "https://github.com/admiralnlson/castle-falkenstein-fvtt/issues",
  "changelog": "https://github.com/admiralnlson/castle-falkenstein-fvtt/releases"
}
